my_first_package_bmi_calculator/__init__.py
my_first_package_bmi_calculator/main.py
my_first_package_bmi_calculator-1.0.0.dist-info/METADATA
my_first_package_bmi_calculator-1.0.0.dist-info/WHEEL
my_first_package_bmi_calculator-1.0.0.dist-info/top_level.txt
my_first_package_bmi_calculator-1.0.0.dist-info/RECORD
