Metadata-Version: 2.1
Name: my-first-package-bmi-calculator
Version: 1.0.0
Summary: Calculates body mass index
Home-page: https://github.com/Wiliam-G/introducao_criacao_de_pacotes
Author: Wiliam_Gomes
Author-email: wiliam.gomes99@gmail.com
Requires-Python: >=3.0
